{
  "rezepte": [
    {
      "titel": "Perfekt gekochte Eier",
      "beschreibung": "Die klassischen Eier mit festem Eiweiß und cremigem Eigelb – ideal für den Alltag.",
      "zutaten": [
        { "name": "Eier", "menge": "4" },
        { "name": "Wasser", "menge": "Genug, um die Eier zu bedecken" },
        { "name": "Salz", "menge": "nach Geschmack" }
      ],
      "zubereitung": [
        "Die Eier vorsichtig in einen Topf legen.",
        "Mit kaltem Wasser bedecken.",
        "Den Topf auf hohe Hitze stellen und das Wasser zum Kochen bringen.",
        "Sobald das Wasser kocht, die Hitze reduzieren und 8-10 Minuten köcheln lassen, je nach gewünschter Konsistenz.",
        "Die Eier sofort in Eiswasser abschrecken, um den Kochvorgang zu stoppen.",
        "Nach dem Abkühlen schälen, mit Salz bestreuen und servieren."
      ],
      "kochzeit": "8-10 Minuten",
      "portionen": 4
    },
    {
      "titel": "Weich gekochte Eier",
      "beschreibung": "Eier mit weichem, leicht fließendem Eigelb – perfekt für ein Frühstück oder als Topping.",
      "zutaten": [
        { "name": "Eier", "menge": "2" },
        { "name": "Wasser", "menge": "Genug, um die Eier zu bedecken" },
        { "name": "Salz", "menge": "nach Geschmack" }
      ],
      "zubereitung": [
        "Die Eier vorsichtig in einen Topf legen.",
        "Mit kaltem Wasser bedecken und zum Kochen bringen.",
        "Sobald das Wasser kocht, die Hitze reduzieren und 4-6 Minuten köcheln lassen, je nach gewünschter Weichheit.",
        "Die Eier sofort in kaltem Wasser abschrecken, damit sie nicht weitergaren.",
        "Schälen, mit einer Prise Salz verfeinern und servieren."
      ],
      "kochzeit": "4-6 Minuten",
      "portionen": 2
    },
    {
      "titel": "Pikant gewürzte Eier",
      "beschreibung": "Hart gekochte Eier, die nach dem Kochen in einer würzigen Marinade eingelegt werden – eine tolle Snack-Variante.",
      "zutaten": [
        { "name": "Eier", "menge": "6" },
        { "name": "Wasser", "menge": "Genug, um die Eier zu bedecken" },
        { "name": "Sojasauce", "menge": "3 EL" },
        { "name": "Sesamöl", "menge": "1 TL" },
        { "name": "Ingwer, frisch gerieben", "menge": "1 TL" },
        { "name": "Knoblauch, fein gehackt", "menge": "1 Zehe" },
        { "name": "Chiliflocken", "menge": "nach Geschmack" }
      ],
      "zubereitung": [
        "Die Eier in einen Topf legen und mit Wasser bedecken.",
        "Zum Kochen bringen und 10 Minuten lang hart kochen.",
        "Die Eier abschrecken, schälen und halbieren.",
        "In einer Schüssel Sojasauce, Sesamöl, geriebenen Ingwer, Knoblauch und Chiliflocken gut vermischen.",
        "Die Eier in die Marinade legen und mindestens 30 Minuten ziehen lassen, damit sie den Geschmack aufnehmen.",
        "Die marinierten Eier als Snack oder als Teil eines Salats servieren."
      ],
      "kochzeit": "10 Minuten Kochzeit plus 30 Minuten Marinierzeit",
      "portionen": 6
    }
  ]
}
